setup.py
Flask_Routing.egg-info/PKG-INFO
Flask_Routing.egg-info/SOURCES.txt
Flask_Routing.egg-info/dependency_links.txt
Flask_Routing.egg-info/not-zip-safe
Flask_Routing.egg-info/requires.txt
Flask_Routing.egg-info/top_level.txt
flask_routing/__init__.py