Metadata-Version: 1.1
Name: Flask-Routing
Version: 0.0.21
Summary: Alternative web.py style routing for Flask
Home-page: UNKNOWN
Author: Hackerlist
Author-email: support@hackerlist.net
License: BSD
Platform: any
Classifier: Development Status :: 2 - Pre-Alpha
Classifier: Environment :: Web Environment
Classifier: Intended Audience :: Developers
Classifier: License :: OSI Approved :: BSD License
Classifier: Operating System :: OS Independent
Classifier: Programming Language :: Python
Classifier: Topic :: Internet :: WWW/HTTP :: Dynamic Content
Classifier: Topic :: Software Development :: Libraries :: Python Modules
